MANIFEST.in
README.rst
setup.py
django_human_datetime.egg-info/PKG-INFO
django_human_datetime.egg-info/SOURCES.txt
django_human_datetime.egg-info/dependency_links.txt
django_human_datetime.egg-info/top_level.txt
humandt/__init__.py
humandt/fields.py
humandt/models.py
humandt/parser.py
humandt/tests.py