Metadata-Version: 1.1
Name: django-human-datetime
Version: 0.1
Summary: Uses the parsedatetime package to parse human readable date/time expressions into Django fields
Home-page: http://github.com/justquick/django-human-datetime
Author: Justin Quick
Author-email: justquick@gmail.com
License: UNKNOWN
Platform: UNKNOWN
Classifier: Development Status :: 4 - Beta
Classifier: Environment :: Web Environment
Classifier: Intended Audience :: Developers
Classifier: License :: OSI Approved :: BSD License
Classifier: Operating System :: OS Independent
Classifier: Programming Language :: Python
Classifier: Topic :: Utilities
Requires: parsedatetime
Requires: pytz
